onnx_diagnostic/__init__.py
onnx_diagnostic/__main__.py
onnx_diagnostic/_command_lines_parser.py
onnx_diagnostic/doc.py
onnx_diagnostic/ext_test_case.py
onnx_diagnostic/typing.py
onnx_diagnostic/ci_models/__init__.py
onnx_diagnostic/ci_models/ci_helpers.py
onnx_diagnostic/ci_models/export_phi4_mm.py
onnx_diagnostic/ci_models/export_qwen25_vl.py
onnx_diagnostic/export/__init__.py
onnx_diagnostic/export/api.py
onnx_diagnostic/export/cf_simple_loop_for.py
onnx_diagnostic/export/control_flow_onnx.py
onnx_diagnostic/export/dynamic_shapes.py
onnx_diagnostic/export/onnx_plug.py
onnx_diagnostic/export/shape_helper.py
onnx_diagnostic/export/validate.py
onnx_diagnostic/helpers/__init__.py
onnx_diagnostic/helpers/_log_helper.py
onnx_diagnostic/helpers/args_helper.py
onnx_diagnostic/helpers/bench_run.py
onnx_diagnostic/helpers/cache_helper.py
onnx_diagnostic/helpers/config_helper.py
onnx_diagnostic/helpers/doc_helper.py
onnx_diagnostic/helpers/dot_helper.py
onnx_diagnostic/helpers/fake_tensor_helper.py
onnx_diagnostic/helpers/graph_helper.py
onnx_diagnostic/helpers/helper.py
onnx_diagnostic/helpers/log_helper.py
onnx_diagnostic/helpers/memory_peak.py
onnx_diagnostic/helpers/mini_onnx_builder.py
onnx_diagnostic/helpers/model_builder_helper.py
onnx_diagnostic/helpers/onnx_helper.py
onnx_diagnostic/helpers/optim_helper.py
onnx_diagnostic/helpers/ort_session.py
onnx_diagnostic/helpers/rt_helper.py
onnx_diagnostic/helpers/torch_fx_graph_helper.py
onnx_diagnostic/helpers/torch_helper.py
onnx_diagnostic/investigate/__init__.py
onnx_diagnostic/investigate/input_observer.py
onnx_diagnostic/reference/__init__.py
onnx_diagnostic/reference/evaluator.py
onnx_diagnostic/reference/ort_evaluator.py
onnx_diagnostic/reference/quantized_tensor.py
onnx_diagnostic/reference/report_results_comparison.py
onnx_diagnostic/reference/torch_evaluator.py
onnx_diagnostic/reference/ops/__init__.py
onnx_diagnostic/reference/ops/op_add_add_mul_mul.py
onnx_diagnostic/reference/ops/op_attention.py
onnx_diagnostic-0.8.11.dist-info/licenses/LICENSE.txt
onnx_diagnostic-0.8.11.dist-info/METADATA
onnx_diagnostic-0.8.11.dist-info/WHEEL
onnx_diagnostic-0.8.11.dist-info/top_level.txt
onnx_diagnostic-0.8.11.dist-info/RECORD
