Metadata-Version: 2.4
Name: onnx-diagnostic
Version: 0.8.11
Summary: Tools to help converting pytorch models into ONNX.
Home-page: https://github.com/sdpython/onnx-diagnostic
Author: Xavier Dupré
Author-email: Xavier Dupré <xavier.dupre@gmail.com>
License: MIT
Project-URL: Homepage, https://sdpython.github.io/doc/onnx-diagnostic/dev/
Project-URL: Repository, https://github.com/sdpython/onnx-diagnostic/
Requires-Python: >=3.9
License-File: LICENSE.txt
Dynamic: author
Dynamic: home-page
Dynamic: license-file
